rxon/__init__.py
rxon/blob.py
rxon/constants.py
rxon/exceptions.py
rxon/models.py
rxon/py.typed
rxon/security.py
rxon/utils.py
rxon/validators.py
rxon/transports/__init__.py
rxon/transports/base.py
rxon/transports/factory.py
rxon/transports/http.py
rxon/transports/http_server.py
rxon-1.0b1.dist-info/licenses/LICENSE
rxon-1.0b1.dist-info/METADATA
rxon-1.0b1.dist-info/WHEEL
rxon-1.0b1.dist-info/top_level.txt
rxon-1.0b1.dist-info/RECORD
