Metadata-Version: 2.4
Name: rxon
Version: 1.0b1
Summary: RXON (Reverse Axon) - Lightweight Inter-node Reverse Communication Protocol.
Author-email: Dmitrii Gagarin <madgagarin@gmail.com>
Maintainer-email: Dmitrii Gagarin <madgagarin@gmail.com>
Project-URL: Homepage, https://github.com/madgagarin/rxon
Project-URL: Repository, https://github.com/madgagarin/rxon
Project-URL: Bug Tracker, https://github.com/madgagarin/rxon/issues
Keywords: rxon,hln,protocol,distributed-systems,holarchy,holon
Classifier: Development Status :: 4 - Beta
Classifier: Intended Audience :: Developers
Classifier: Intended Audience :: System Administrators
Classifier: Programming Language :: Python :: 3
Classifier: Programming Language :: Python :: 3.11
Classifier: Programming Language :: Python :: 3.12
Classifier: License :: OSI Approved :: MIT License
Classifier: Operating System :: OS Independent
Classifier: Typing :: Typed
Requires-Python: >=3.11
License-File: LICENSE
Requires-Dist: aiohttp>=3.12
Requires-Dist: orjson>=3.10
Dynamic: license-file
